MANIFEST.in
README.md
setup.py
ExoScanner/Exoscanner_logo.png
ExoScanner/__init__.py
ExoScanner/__main__.py
ExoScanner/analyzeLightCurves.py
ExoScanner/config.py
ExoScanner/data.py
ExoScanner/generateBrightnessOfAllStarsInAllImages.py
ExoScanner/generateCatalogs.py
ExoScanner/generateField.py
ExoScanner/generateLightCurves.py
ExoScanner/getBrightnessOfOneStarInField.py
ExoScanner/getCoordinates.py
ExoScanner/getFilelist.py
ExoScanner/getTimeOfObservation.py
ExoScanner/gui.py
ExoScanner/mergeCatalogs.py
ExoScanner/myAlgorithms.py
ExoScanner/output.py
ExoScanner/readImage.py
ExoScanner/run.py
ExoScanner.egg-info/PKG-INFO
ExoScanner.egg-info/SOURCES.txt
ExoScanner.egg-info/dependency_links.txt
ExoScanner.egg-info/requires.txt
ExoScanner.egg-info/top_level.txt