Metadata-Version: 1.1
Name: ExoScanner
Version: 0.2.5
Summary: A program to analyze an image-series for exoplanet transits.
Home-page: https://github.com/josia-john/ExoScanner
Author: Josia John
Author-email: me@jlabs.anonaddy.com
License: UNKNOWN
Platform: UNKNOWN
Classifier: Development Status :: 3 - Alpha
Classifier: Environment :: Console
Classifier: Intended Audience :: Science/Research
Classifier: License :: OSI Approved :: GNU General Public License v3 (GPLv3)
Classifier: Programming Language :: Python :: 3
